numpy_allocator.cpython-38-x86_64-linux-gnu.so
numpy_allocator-1.2.1.dist-info/LICENSE
numpy_allocator-1.2.1.dist-info/METADATA
numpy_allocator-1.2.1.dist-info/RECORD
numpy_allocator-1.2.1.dist-info/WHEEL
numpy_allocator-1.2.1.dist-info/NOTICE
numpy_allocator-1.2.1.dist-info/top_level.txt
